indian_pincode_finder/__init__.py
indian_pincode_finder/indian_pincode_finder.py
indian_pincode_finder/data/__init__.py
indian_pincode_finder/data/india_pincode_final.csv
indian_pincode_finder-0.2.1.dist-info/METADATA
indian_pincode_finder-0.2.1.dist-info/WHEEL
indian_pincode_finder-0.2.1.dist-info/top_level.txt
indian_pincode_finder-0.2.1.dist-info/RECORD
