Metadata-Version: 2.1
Name: indian_pincode_finder
Version: 0.2.1
Summary: Finds state, city , district and pincode of India
Home-page: https://github.com/aimlhoney/IndianPincodeFinder
Author: Honey Kumar
Author-email: sdithoney@gmail.com
Classifier: Programming Language :: Python :: 3
Classifier: Operating System :: OS Independent
Requires-Python: >=3.9
Requires-Dist: numpy>=2.0.2
Requires-Dist: pandas>=2.2.3
